pysignalscope/__init__.py
pysignalscope/channelshift.py
pysignalscope/colors.py
pysignalscope/functions.py
pysignalscope/generalplotsettings.py
pysignalscope/impedance.py
pysignalscope/impedance_dataclass.py
pysignalscope/logconfig.py
pysignalscope/scope.py
pysignalscope/scope_dataclass.py
pysignalscope-0.2.1.dist-info/METADATA
pysignalscope-0.2.1.dist-info/WHEEL
pysignalscope-0.2.1.dist-info/RECORD
