Metadata-Version: 2.3
Name: pysignalscope
Version: 0.2.1
Summary: View, edit and calculate scope results from simulations or real measurements.
Project-URL: Homepage, https://github.com/upb-lea/pySignalScope
Project-URL: Issues, https://github.com/upb-lea/pySignalScope/issues
Author-email: LEA - Paderborn University <upblea@mail.upb.de>
Classifier: License :: OSI Approved :: MIT License
Classifier: Operating System :: OS Independent
Classifier: Programming Language :: Python :: 3
Requires-Python: >=3.8
Requires-Dist: findiff
Requires-Dist: lecroyutils
Requires-Dist: matplotlib
Requires-Dist: numpy
Requires-Dist: scipy
